{
  "$schema": "https://developer.microsoft.com/json-schemas/fabric/item/report/definition/visualContainer/2.5.0/schema.json",
  "name": "8cba269179b52174d26d",
  "position": {
    "x": 688,
    "y": 16,
    "z": 9000,
    "height": 32,
    "width": 144,
    "tabOrder": 10000
  },
  "visual": {
    "visualType": "image",
    "objects": {
      "image": [
        {
          "properties": {
            "sourceFile": {
              "image": {
                "name": {
                  "expr": {
                    "Literal": {
                      "Value": "'database-security.png'"
                    }
                  }
                },
                "url": {
                  "expr": {
                    "ResourcePackageItem": {
                      "PackageName": "RegisteredResources",
                      "PackageType": 1,
                      "ItemName": "database-security47847960909953047.png"
                    }
                  }
                },
                "scaling": {
                  "expr": {
                    "Literal": {
                      "Value": "'Normal'"
                    }
                  }
                }
              }
            }
          }
        }
      ]
    },
    "drillFilterOtherVisuals": true
  }
}